CHANGES.rst
LICENSE
MANIFEST.in
README.rst
setup.py
WTForms_Test.egg-info/SOURCES.txt
docs/Makefile
docs/conf.py
docs/index.rst
docs/make.bat
wtforms_test/__init__.py
wtforms_test.egg-info/PKG-INFO
wtforms_test.egg-info/SOURCES.txt
wtforms_test.egg-info/dependency_links.txt
wtforms_test.egg-info/not-zip-safe
wtforms_test.egg-info/requires.txt
wtforms_test.egg-info/top_level.txt